pulumi_libvirt/__init__.py
pulumi_libvirt/_inputs.py
pulumi_libvirt/_utilities.py
pulumi_libvirt/cloud_init_disk.py
pulumi_libvirt/combustion.py
pulumi_libvirt/domain.py
pulumi_libvirt/get_network_dns_host_template.py
pulumi_libvirt/get_network_dns_srv_template.py
pulumi_libvirt/get_network_dnsmasq_options_template.py
pulumi_libvirt/get_node_device_info.py
pulumi_libvirt/get_node_devices.py
pulumi_libvirt/get_node_info.py
pulumi_libvirt/ignition.py
pulumi_libvirt/network.py
pulumi_libvirt/outputs.py
pulumi_libvirt/pool.py
pulumi_libvirt/provider.py
pulumi_libvirt/pulumi-plugin.json
pulumi_libvirt/py.typed
pulumi_libvirt/volume.py
pulumi_libvirt/config/__init__.py
pulumi_libvirt/config/__init__.pyi
pulumi_libvirt/config/vars.py
pulumi_libvirt-0.5.4.dist-info/METADATA
pulumi_libvirt-0.5.4.dist-info/WHEEL
pulumi_libvirt-0.5.4.dist-info/top_level.txt
pulumi_libvirt-0.5.4.dist-info/RECORD
