Metadata-Version: 2.1
Name: pulumi_libvirt
Version: 0.5.4
Summary: A Pulumi package for creating and managing libvirt cloud resources.
License: Apache-2.0
Project-URL: Homepage, https://pulumi.io
Project-URL: Repository, https://github.com/pulumi/pulumi-libvirt
Keywords: pulumi,libvirt
Requires-Python: >=3.9
Requires-Dist: parver>=0.2.1
Requires-Dist: pulumi<4.0.0,>=3.142.0
Requires-Dist: semver>=2.8.1
Requires-Dist: typing-extensions>=4.11; python_version < "3.11"
